dsfinfo/__init__.py
dsfinfo/dsfinfo.py
dsfinfo-0.0.4.dist-info/LICENSE
dsfinfo-0.0.4.dist-info/METADATA
dsfinfo-0.0.4.dist-info/WHEEL
dsfinfo-0.0.4.dist-info/top_level.txt
dsfinfo-0.0.4.dist-info/RECORD
