Metadata-Version: 2.1
Name: dsfinfo
Version: 0.0.4
Summary: Run the info() method to disply Data Science Foundations links.
Home-page: https://github.com/jknudstrup/dsf_info
Author: Jim Knudstrup
Author-email: jim.knudstrup@gmail.com
License: UNKNOWN
Platform: UNKNOWN
Classifier: Programming Language :: Python :: 3
Classifier: License :: OSI Approved :: MIT License
Classifier: Operating System :: OS Independent
